tmux_mcp_tools/__init__.py
tmux_mcp_tools/config.py
tmux_mcp_tools/server.py
tmux_mcp_tools/tools.py
tmux_mcp_tools/utils.py
tmux_mcp_tools-0.4.1.dist-info/METADATA
tmux_mcp_tools-0.4.1.dist-info/WHEEL
tmux_mcp_tools-0.4.1.dist-info/entry_points.txt
tmux_mcp_tools-0.4.1.dist-info/licenses/LICENSE
tmux_mcp_tools-0.4.1.dist-info/RECORD
