Metadata-Version: 2.4
Name: tmux-mcp-tools
Version: 0.4.1
Summary: MCP server for tmux operations
License: MIT
License-File: LICENSE
Requires-Python: >=3.10
Requires-Dist: fastmcp
